example_pkg/__init__.py
example_pkg/arithmetic.py
jfamb_utils-1.0.0.dist-info/METADATA
jfamb_utils-1.0.0.dist-info/WHEEL
jfamb_utils-1.0.0.dist-info/top_level.txt
jfamb_utils-1.0.0.dist-info/RECORD
