Metadata-Version: 2.1
Name: jfamb-utils
Version: 1.0.0
Summary: Test to understand PyPI packages dependencies
Home-page: https://github.com/pypa/sampleproject
Author: Jonas Freire
Author-email: jonasfreireperson@gmail.com
License: UNKNOWN
Platform: UNKNOWN
Classifier: Programming Language :: Python :: 3
Classifier: License :: OSI Approved :: MIT License
Classifier: Operating System :: OS Independent
Requires-Python: >=3.6
Requires-Dist: simple-sum
